setup.cfg
setup.py
./abook.py
./distribute_setup.py
./pypeople.py
./pyple_unittest.py
pypeople.egg-info/PKG-INFO
pypeople.egg-info/SOURCES.txt
pypeople.egg-info/dependency_links.txt
pypeople.egg-info/requires.txt
pypeople.egg-info/top_level.txt