Metadata-Version: 1.0
Name: pypeople
Version: 0.6.2-1
Summary: Commandline vCard editor in Python, with git syncing
Home-page: http://github.com/farmckon/pyple
Author: Far McKon
Author-email: farMcKon@gmail.com
License: AGPL
Platform: a
Platform: n
Platform: y
Classifier: Development Status :: 3 - Alpha
Classifier: Intended Audience :: Developers
Classifier: Intended Audience :: End Users/Desktop
Classifier: License :: OSI Approved :: GNU Affero General Public License v3 or later (AGPLv3+)
Classifier: Natural Language :: English
Classifier: Operating System :: POSIX
Classifier: Operating System :: Microsoft :: Windows
Classifier: Programming Language :: Python
Classifier: Programming Language :: Python :: 2.6
Classifier: Programming Language :: Python :: 2.7
Classifier: Topic :: Communications :: Email :: Address Book
Classifier: Topic :: Software Development :: Libraries
Classifier: Topic :: Database
Classifier: Topic :: Utilities
